[
  {
    "date": "2026-06-29",
    "day": 1,
    "menus": [
      "쌀밥/햄부대찌개",
      "청피망고기산적볶음",
      "알감자오븐구이",
      "숙주나물무침/배추김치",
      "초코패스츄리빵/하루견과/쌀과자/사과주스"
    ],
    "calorie": 1057,
    "time": 1,
    "restaurant_name": "기숙사_식당_한식"
  },
  {
    "date": "2026-06-29",
    "day": 1,
    "menus": [
      "쌀밥",
      "시래기두부장국",
      "대패불고기야채찜&유자폰즈S",
      "톳으깬두부범벅",
      "새콤오이상추겉절이",
      "배추김치"
    ],
    "calorie": 952,
    "time": 2,
    "restaurant_name": "기숙사_식당_한식"
  },
  {
    "date": "2026-06-29",
    "day": 1,
    "menus": [
      "한그릇)치킨마요덮밥",
      "유부무채국",
      "매콤한입떡볶이",
      "치커리유자샐러드",
      "반달단무지",
      "수제마늘빵"
    ],
    "calorie": 1091,
    "time": 3,
    "restaurant_name": "기숙사_식당_한식"
  },
  {
    "date": "2026-06-30",
    "day": 2,
    "menus": [
      "곤드레나물밥/콩가루배추국",
      "두부적브로콜리강정",
      "부추어묵잡채",
      "도시락김/배추김치",
      "치즈롤빵/어묵핫바/쌀과자/요구르트"
    ],
    "calorie": 944,
    "time": 1,
    "restaurant_name": "기숙사_식당_한식"
  },
  {
    "date": "2026-06-30",
    "day": 2,
    "menus": [
      "흑미쌀밥",
      "돈육김치찌개",
      "야채계란말이*케찹",
      "들기름막국수",
      "양념깻잎지무침",
      "배추김치"
    ],
    "calorie": 1030,
    "time": 2,
    "restaurant_name": "기숙사_식당_한식"
  },
  {
    "date": "2026-06-30",
    "day": 2,
    "menus": [
      "쌀밥",
      "얼큰계란국",
      "숯불향돼지불고기",
      "갈릭칩볼어묵강정",
      "콩나물겨자냉채",
      "배추김치"
    ],
    "calorie": 1082,
    "time": 3,
    "restaurant_name": "기숙사_식당_한식"
  },
  {
    "date": "2026-07-01",
    "day": 3,
    "menus": [
      "쌀밥/황태채콩나물국",
      "통살새우커틀렛*타르S",
      "매콤두부조림",
      "비타민겉절이/배추김치",
      "미니꿀호떡/삼각김밥/포도주스"
    ],
    "calorie": 934,
    "time": 1,
    "restaurant_name": "기숙사_식당_한식"
  },
  {
    "date": "2026-07-01",
    "day": 3,
    "menus": [
      "한그릇)김치말이냉국수",
      "추가쌀밥",
      "&비빔두부강된장",
      "고기메밀전병구이",
      "양념마늘쫑무침",
      "반달단무지"
    ],
    "calorie": 993,
    "time": 2,
    "restaurant_name": "기숙사_식당_한식"
  },
  {
    "date": "2026-07-01",
    "day": 3,
    "menus": [
      "쌀밥",
      "김치수제비국",
      "롱그릴소시지구이",
      "계란야채스크램블",
      "부추겉절이",
      "깍두기"
    ],
    "calorie": 917,
    "time": 3,
    "restaurant_name": "기숙사_식당_한식"
  },
  {
    "date": "2026-07-02",
    "day": 4,
    "menus": [
      "큰그릇)맑은닭곰탕&당면사리/쌀밥",
      "김말이깐풍기강정",
      "아삭고추쌈장무침/깍두기",
      "고구마케익빵/구운란/쌀과자/요구르트"
    ],
    "calorie": 947,
    "time": 1,
    "restaurant_name": "기숙사_식당_한식"
  },
  {
    "date": "2026-07-02",
    "day": 4,
    "menus": [
      "한그릇)불고기마늘쫑비빔밥",
      "(돈불고기,마늘쫑,상추,쌀밥)",
      "근대된장국",
      "부추야채계란찜",
      "매콤새송이버섯볶음",
      "배추김치"
    ],
    "calorie": 970,
    "time": 2,
    "restaurant_name": "기숙사_식당_한식"
  },
  {
    "date": "2026-07-02",
    "day": 4,
    "menus": [
      "후리가케밥",
      "미역두부장국",
      "등심돈까스*매콤S",
      "오리엔탈냉우동샐러드",
      "배추김치",
      "자몽아이스티"
    ],
    "calorie": 1056,
    "time": 3,
    "restaurant_name": "기숙사_식당_한식"
  },
  {
    "date": "2026-07-03",
    "day": 5,
    "menus": [
      "쌀밥/소고기시락국",
      "해물동그랑땡조림",
      "오징어어묵볶음",
      "우엉채조림/배추김치",
      "갈릭소보로빵/쌀약과/딸기우유"
    ],
    "calorie": 946,
    "time": 1,
    "restaurant_name": "기숙사_식당_한식"
  },
  {
    "date": "2026-07-03",
    "day": 5,
    "menus": [
      "쌀밥",
      "콩나물무채국",
      "고추장돼지불고기",
      "시나몬고구마떡맛탕",
      "다시마채무침",
      "배추김치"
    ],
    "calorie": 1047,
    "time": 2,
    "restaurant_name": "기숙사_식당_한식"
  },
  {
    "date": "2026-07-03",
    "day": 5,
    "menus": [
      "쌀밥",
      "얼큰닭개장",
      "임꺽정떡갈비구이",
      "온두부찜*양념장",
      "참치김치볶음",
      "미니도시락김1EA"
    ],
    "calorie": 930,
    "time": 3,
    "restaurant_name": "기숙사_식당_한식"
  },
  {
    "date": "2026-07-04",
    "day": 6,
    "menus": [
      "쌀밥",
      "계란떡만둣국",
      "고등어구이*와사비간장",
      "쥐어채조림",
      "도토리묵야채무침",
      "배추김치"
    ],
    "calorie": 1055,
    "time": 1,
    "restaurant_name": "기숙사_식당_한식"
  },
  {
    "date": "2026-07-04",
    "day": 6,
    "menus": [
      "쌀밥",
      "순살감자탕",
      "매콤순대야채볶음",
      "땅콩멸치조림",
      "얼갈이오이생채",
      "배추김치"
    ],
    "calorie": 925,
    "time": 2,
    "restaurant_name": "기숙사_식당_한식"
  },
  {
    "date": "2026-07-04",
    "day": 6,
    "menus": [
      "쌀밥",
      "차돌된장찌개",
      "브로콜리소시지볶음",
      "간장누들떡볶이",
      "새콤상추겉절이",
      "배추김치"
    ],
    "calorie": 1046,
    "time": 3,
    "restaurant_name": "기숙사_식당_한식"
  },
  {
    "date": "2026-07-05",
    "day": 7,
    "menus": [
      "쌀밥",
      "김치콩나물국",
      "계란장조림2EA",
      "미트볼양념떡강정",
      "얼갈이생채",
      "배추김치"
    ],
    "calorie": 946,
    "time": 1,
    "restaurant_name": "기숙사_식당_한식"
  },
  {
    "date": "2026-07-05",
    "day": 7,
    "menus": [
      "쌀밥",
      "팽이미소장국",
      "순살치킨까스&소스",
      "돈육카레소스",
      "치커리흑임자샐러드",
      "배추김치"
    ],
    "calorie": 970,
    "time": 2,
    "restaurant_name": "기숙사_식당_한식"
  },
  {
    "date": "2026-07-05",
    "day": 7,
    "menus": [
      "쌀밥",
      "미역국",
      "김치제육볶음",
      "감자고로케*케찹",
      "숙주나물무침",
      "오복지"
    ],
    "calorie": 1011,
    "time": 3,
    "restaurant_name": "기숙사_식당_한식"
  }
]